pythonanywhere_mcp_server/__init__.py
pythonanywhere_mcp_server/__main__.py
pythonanywhere_mcp_server/server.py
pythonanywhere_mcp_server/tools/__init__.py
pythonanywhere_mcp_server/tools/file.py
pythonanywhere_mcp_server/tools/schedule.py
pythonanywhere_mcp_server/tools/webapp.py
pythonanywhere_mcp_server/tools/website.py
pythonanywhere_mcp_server-0.0.8.dist-info/licenses/LICENSE
pythonanywhere_mcp_server-0.0.8.dist-info/METADATA
pythonanywhere_mcp_server-0.0.8.dist-info/WHEEL
pythonanywhere_mcp_server-0.0.8.dist-info/entry_points.txt
pythonanywhere_mcp_server-0.0.8.dist-info/top_level.txt
pythonanywhere_mcp_server-0.0.8.dist-info/RECORD
