Metadata-Version: 2.4
Name: pythonanywhere-mcp-server
Version: 0.0.8
Summary: PythonAnywhere Model Context Protocol Server
Author-email: PythonAnywhere Developers <developers@pythonanywhere.com>
License-Expression: MIT
Project-URL: Homepage, https://github.com/pythonanywhere/pythonanywhere-mcp-server
Project-URL: Repository, https://github.com/pythonanywhere/pythonanywhere-mcp-server
Project-URL: Documentation, https://github.com/pythonanywhere/pythonanywhere-mcp-server#readme
Project-URL: Issues, https://github.com/pythonanywhere/pythonanywhere-mcp-server/issues
Project-URL: Changelog, https://github.com/pythonanywhere/pythonanywhere-mcp-server/releases
Classifier: Development Status :: 2 - Pre-Alpha
Classifier: Intended Audience :: Developers
Classifier: Programming Language :: Python :: 3.13
Classifier: Topic :: Scientific/Engineering :: Artificial Intelligence
Classifier: Topic :: Utilities
Requires-Python: >=3.13
License-File: LICENSE
Requires-Dist: pythonanywhere-core>=0.2.9
Requires-Dist: mcp[cli]
Provides-Extra: test
Requires-Dist: pytest; extra == "test"
Requires-Dist: pytest-mock; extra == "test"
Dynamic: license-file
